autocut3d/__init__.py
autocut3d/autocut3d.py
autocut3d-0.1.0.dist-info/AUTHORS.rst
autocut3d-0.1.0.dist-info/LICENSE
autocut3d-0.1.0.dist-info/METADATA
autocut3d-0.1.0.dist-info/WHEEL
autocut3d-0.1.0.dist-info/top_level.txt
autocut3d-0.1.0.dist-info/RECORD
