Metadata-Version: 2.1
Name: autocut3d
Version: 0.1.0
Summary: a 3D segmentation algorithm based on cellular automata.
Home-page: https://github.com/edsoncavalcanti/autocut3d
Author: Edson Cavalcanti Neto
Author-email: edsoncavalcanti@hotmail.com
License: MIT license
Keywords: autocut3d
Platform: UNKNOWN
Classifier: Development Status :: 2 - Pre-Alpha
Classifier: Intended Audience :: Developers
Classifier: License :: OSI Approved :: MIT License
Classifier: Natural Language :: English
Classifier: Programming Language :: Python :: 3
Classifier: Programming Language :: Python :: 3.5
Classifier: Programming Language :: Python :: 3.6
Classifier: Programming Language :: Python :: 3.7
Classifier: Programming Language :: Python :: 3.8
Requires-Python: >=3.5
Requires-Dist: pip (==19.2.3)
Requires-Dist: bump2version (==0.5.11)
Requires-Dist: wheel (==0.33.6)
Requires-Dist: watchdog (==0.9.0)
Requires-Dist: flake8 (==3.7.8)
Requires-Dist: tox (==3.14.0)
Requires-Dist: coverage (==4.5.4)
Requires-Dist: Sphinx (==1.8.5)
Requires-Dist: twine (==1.14.0)
Requires-Dist: pytest (==4.6.5)
Requires-Dist: pytest-runner (==5.1)
